CHANGELOG.md
Dockerfile
DockerfileUsage.md
LICENCE
README.md
castor_extractor/__init__.py
castor_extractor/commands/__init__.py
castor_extractor/commands/extract_bigquery.py
castor_extractor/commands/extract_confluence.py
castor_extractor/commands/extract_count.py
castor_extractor/commands/extract_databricks.py
castor_extractor/commands/extract_domo.py
castor_extractor/commands/extract_looker.py
castor_extractor/commands/extract_looker_studio.py
castor_extractor/commands/extract_metabase_api.py
castor_extractor/commands/extract_metabase_db.py
castor_extractor/commands/extract_mode.py
castor_extractor/commands/extract_mysql.py
castor_extractor/commands/extract_notion.py
castor_extractor/commands/extract_postgres.py
castor_extractor/commands/extract_powerbi.py
castor_extractor/commands/extract_qlik.py
castor_extractor/commands/extract_redshift.py
castor_extractor/commands/extract_salesforce.py
castor_extractor/commands/extract_salesforce_reporting.py
castor_extractor/commands/extract_sigma.py
castor_extractor/commands/extract_snowflake.py
castor_extractor/commands/extract_sqlserver.py
castor_extractor/commands/extract_strategy.py
castor_extractor/commands/extract_tableau.py
castor_extractor/commands/extract_thoughtspot.py
castor_extractor/commands/file_check.py
castor_extractor/commands/upload.py
castor_extractor/exceptions.py
castor_extractor/file_checker/__init__.py
castor_extractor/file_checker/column.py
castor_extractor/file_checker/column_test.py
castor_extractor/file_checker/constants.py
castor_extractor/file_checker/enums.py
castor_extractor/file_checker/file.py
castor_extractor/file_checker/file_test.py
castor_extractor/file_checker/file_test_users.csv
castor_extractor/file_checker/file_test_users_valid.csv
castor_extractor/file_checker/templates/__init__.py
castor_extractor/file_checker/templates/generic_warehouse.py
castor_extractor/knowledge/__init__.py
castor_extractor/knowledge/confluence/__init__.py
castor_extractor/knowledge/confluence/assets.py
castor_extractor-0.26.11.dist-info/LICENCE
castor_extractor-0.26.11.dist-info/METADATA
castor_extractor-0.26.11.dist-info/WHEEL
castor_extractor-0.26.11.dist-info/entry_points.txt
castor_extractor-0.26.11.dist-info/RECORD
