Metadata-Version: 2.1
Name: castor-extractor
Version: 0.26.11
Summary: Extract your metadata assets.
Home-page: https://www.castordoc.com/
License: EULA
Author: Castor
Author-email: support@castordoc.com
Requires-Python: >=3.10,<3.14
Classifier: License :: Other/Proprietary License
Classifier: Operating System :: OS Independent
Classifier: Programming Language :: Python :: 3
Classifier: Programming Language :: Python :: 3.10
Classifier: Programming Language :: Python :: 3.11
Classifier: Programming Language :: Python :: 3.12
Classifier: Programming Language :: Python :: 3.13
Provides-Extra: all
Provides-Extra: bigquery
Provides-Extra: count
Provides-Extra: databricks
Provides-Extra: dbt
Provides-Extra: looker
Provides-Extra: lookerstudio
Provides-Extra: metabase
Provides-Extra: mysql
Provides-Extra: postgres
Provides-Extra: powerbi
Provides-Extra: qlik
Provides-Extra: redshift
Provides-Extra: snowflake
Provides-Extra: sqlserver
Provides-Extra: strategy
Provides-Extra: tableau
Requires-Dist: cryptography (>=43.0.0,<44.0.0) ; extra == "snowflake"
Requires-Dist: databricks-sql-connector (==3.6.0) ; extra == "databricks" or extra == "all"
Requires-Dist: google-api-core (>=2.1.1,<3.0.0)
Requires-Dist: google-api-python-client (>=2.121.0,<3.0.0) ; extra == "lookerstudio" or extra == "all"
Requires-Dist: google-auth (>=2,<3)
Requires-Dist: google-cloud-core (>=2.1.0,<3.0.0)
Requires-Dist: google-resumable-media (>=2.0.3,<3.0.0)
Requires-Dist: googleapis-common-protos (>=1.53.0,<2.0.0)
Requires-Dist: looker-sdk (>=25.0.0,<26.0.0) ; extra == "looker" or extra == "all"
Requires-Dist: msal (>=1.20.0,<2.0.0) ; extra == "powerbi" or extra == "all"
Requires-Dist: mstrio-py (>=11.5.3.101,<12.0.0.0) ; (python_version >= "3.10") and (extra == "strategy" or extra == "all")
Requires-Dist: numpy (<2) ; extra == "bigquery" or extra == "databricks" or extra == "all"
Requires-Dist: numpy (>=1.26) ; (python_version >= "3.12" and python_version < "3.13") and (extra == "bigquery" or extra == "databricks" or extra == "all")
Requires-Dist: pandas (>=2.1) ; (python_version >= "3.12" and python_version < "3.13") and (extra == "databricks" or extra == "all")
Requires-Dist: psycopg2-binary (>=2.0.0,<3.0.0) ; extra == "metabase" or extra == "postgres" or extra == "redshift" or extra == "all"
Requires-Dist: pycryptodome (>=3.0.0,<4.0.0) ; extra == "metabase" or extra == "all"
Requires-Dist: pydantic (>=2.6,<3.0)
Requires-Dist: pydantic-settings (>=2.2,<3.0)
Requires-Dist: pymssql (>=2.2.11,<3.0.0) ; extra == "sqlserver" or extra == "all"
Requires-Dist: pymysql[rsa] (>=1.1.0,<2.0.0) ; extra == "mysql" or extra == "all"
Requires-Dist: python-dateutil (>=2.0.0,<=3.0.0)
Requires-Dist: requests (>=2.0.0,<3.0.0)
Requires-Dist: setuptools (>=78.1)
Requires-Dist: snowflake-connector-python (>=3.4.0,<4.0.0) ; extra == "snowflake" or extra == "all"
Requires-Dist: snowflake-sqlalchemy (!=1.2.5,<2.0.0) ; extra == "snowflake" or extra == "all"
Requires-Dist: sqlalchemy (>=1.4,<1.5)
Requires-Dist: sqlalchemy-bigquery[bqstorage] (>=1.0.0,<=2.0.0) ; extra == "bigquery" or extra == "count" or extra == "all"
Requires-Dist: sqlalchemy-redshift (>=0.8.14,<0.9.0) ; extra == "redshift" or extra == "all"
Requires-Dist: tableauserverclient (>=0.25.0,<0.26.0) ; extra == "tableau" or extra == "all"
Requires-Dist: tqdm (>=4.0.0,<5.0.0)
Requires-Dist: websocket-client (>=1,<2) ; extra == "qlik" or extra == "all"
Project-URL: Documentation, https://docs.castordoc.com/castor-package/castor-extractor
